{"teams": ["MIA", "TB"], "stats": [{"sequence": 4, "clubcode": "MIA", "playerName": "J.Lane", "statId": 52, "yards": 0, "gameId": "2012120207"}, {"sequence": 6, "clubcode": "MIA", "playerName": "J.Lane", "statId": 55, "yards": 0, "gameId": "2012120207"}, {"sequence": 7, "clubcode": "MIA", "playerName": "J.Lane", "statId": 21, "yards": 2, "gameId": "2012120207"}, {"sequence": 8, "clubcode": "MIA", "playerName": "J.Lane", "statId": 115, "yards": 0, "gameId": "2012120207"}, {"sequence": 9, "clubcode": "MIA", "playerName": "J.Lane", "statId": 113, "yards": 0, "gameId": "2012120207"}, {"sequence": 3, "clubcode": "MIA", "playerName": "J.Lane", "statId": 21, "yards": 7, "gameId": "2012101405"}, {"sequence": 4, "clubcode": "MIA", "playerName": "J.Lane", "statId": 115, "yards": 0, "gameId": "2012101405"}, {"sequence": 5, "clubcode": "MIA", "playerName": "J.Lane", "statId": 113, "yards": 1, "gameId": "2012101405"}, {"sequence": 3, "clubcode": "MIA", "playerName": "J.Lane", "statId": 21, "yards": 5, "gameId": "2012101405"}, {"sequence": 4, "clubcode": "MIA", "playerName": "J.Lane", "statId": 115, "yards": 0, "gameId": "2012101405"}, {"sequence": 5, "clubcode": "MIA", "playerName": "J.Lane", "statId": 113, "yards": 3, "gameId": "2012101405"}, {"sequence": 2, "clubcode": "TB", "playerName": "J.Lane", "statId": 10, "yards": 1, "gameId": "2014080802"}, {"sequence": 1, "clubcode": "MIA", "playerName": "J.Lane", "statId": 10, "yards": 3, "gameId": "2012091612"}, {"sequence": 1, "clubcode": "MIA", "playerName": "J.Lane", "statId": 10, "yards": 3, "gameId": "2012091612"}, {"sequence": 2, "clubcode": "MIA", "playerName": "J.Lane", "statId": 10, "yards": 2, "gameId": "2012091612"}, {"sequence": 3, "clubcode": "MIA", "playerName": "J.Lane", "statId": 10, "yards": 4, "gameId": "2012091612"}, {"sequence": 3, "clubcode": "MIA", "playerName": "J.Lane", "statId": 21, "yards": 2, "gameId": "2012121605"}, {"sequence": 4, "clubcode": "MIA", "playerName": "J.Lane", "statId": 115, "yards": 0, "gameId": "2012121605"}, {"sequence": 5, "clubcode": "MIA", "playerName": "J.Lane", "statId": 113, "yards": 0, "gameId": "2012121605"}, {"sequence": 4, "clubcode": "MIA", "playerName": "J.Lane", "statId": 22, "yards": 4, "gameId": "2012121605"}, {"sequence": 5, "clubcode": "MIA", "playerName": "J.Lane", "statId": 115, "yards": 0, "gameId": "2012121605"}, {"sequence": 6, "clubcode": "MIA", "playerName": "J.Lane", "statId": 113, "yards": 0, "gameId": "2012121605"}, {"sequence": 1, "clubcode": "MIA", "playerName": "J.Lane", "statId": 93, "yards": 5, "gameId": "2012121605"}, {"sequence": 2, "clubcode": "TB", "playerName": "J.Lane", "statId": 10, "yards": 54, "gameId": "2014090711"}, {"sequence": 1, "clubcode": "MIA", "playerName": "J.Lane", "statId": 82, "yards": 0, "gameId": "2012102801"}, {"sequence": 1, "clubcode": "MIA", "playerName": "J.Lane", "statId": 113, "yards": 10, "gameId": "2012082953"}, {"sequence": 2, "clubcode": "MIA", "playerName": "J.Lane", "statId": 21, "yards": 12, "gameId": "2012082953"}, {"sequence": 6, "clubcode": "MIA", "playerName": "J.Lane", "statId": 115, "yards": 0, "gameId": "2012082953"}, {"sequence": 4, "clubcode": "MIA", "playerName": "J.Lane", "statId": 10, "yards": -5, "gameId": "2012100705"}, {"sequence": 6, "clubcode": "MIA", "playerName": "J.Lane", "statId": 106, "yards": 0, "gameId": "2012100705"}, {"sequence": 8, "clubcode": "MIA", "playerName": "J.Lane", "statId": 52, "yards": 0, "gameId": "2012100705"}, {"sequence": 4, "clubcode": "MIA", "playerName": "J.Lane", "statId": 21, "yards": 15, "gameId": "2012100705"}, {"sequence": 5, "clubcode": "MIA", "playerName": "J.Lane", "statId": 115, "yards": 0, "gameId": "2012100705"}, {"sequence": 6, "clubcode": "MIA", "playerName": "J.Lane", "statId": 113, "yards": 13, "gameId": "2012100705"}, {"sequence": 2, "clubcode": "MIA", "playerName": "J.Lane", "statId": 10, "yards": 0, "gameId": "2012100705"}, {"sequence": 3, "clubcode": "MIA", "playerName": "J.Lane", "statId": 21, "yards": 5, "gameId": "2012100705"}, {"sequence": 4, "clubcode": "MIA", "playerName": "J.Lane", "statId": 115, "yards": 0, "gameId": "2012100705"}, {"sequence": 5, "clubcode": "MIA", "playerName": "J.Lane", "statId": 113, "yards": 3, "gameId": "2012100705"}, {"sequence": 3, "clubcode": "MIA", "playerName": "J.Lane", "statId": 10, "yards": 1, "gameId": "2012081753"}, {"sequence": 3, "clubcode": "MIA", "playerName": "J.Lane", "statId": 79, "yards": 0, "gameId": "2012081753"}, {"sequence": 1, "clubcode": "MIA", "playerName": "J.Lane", "statId": 10, "yards": 3, "gameId": "2012092306"}, {"sequence": 2, "clubcode": "MIA", "playerName": "J.Lane", "statId": 11, "yards": 1, "gameId": "2012092306"}, {"sequence": 3, "clubcode": "MIA", "playerName": "J.Lane", "statId": 21, "yards": 1, "gameId": "2012092306"}, {"sequence": 4, "clubcode": "MIA", "playerName": "J.Lane", "statId": 115, "yards": 0, "gameId": "2012092306"}, {"sequence": 5, "clubcode": "MIA", "playerName": "J.Lane", "statId": 113, "yards": 1, "gameId": "2012092306"}, {"sequence": 2, "clubcode": "MIA", "playerName": "J.Lane", "statId": 10, "yards": 0, "gameId": "2012111102"}, {"sequence": 4, "clubcode": "MIA", "playerName": "J.Lane", "statId": 52, "yards": 0, "gameId": "2012120910"}, {"sequence": 5, "clubcode": "MIA", "playerName": "J.Lane", "statId": 45, "yards": 24, "gameId": "2012120910"}, {"sequence": 6, "clubcode": "MIA", "playerName": "J.Lane", "statId": 55, "yards": 0, "gameId": "2012120910"}, {"sequence": 3, "clubcode": "TB", "playerName": "J.Lane", "statId": 79, "yards": 0, "gameId": "2015110105"}, {"sequence": 2, "clubcode": "MIA", "playerName": "J.Lane", "statId": 10, "yards": 1, "gameId": "2012093007"}, {"sequence": 3, "clubcode": "MIA", "playerName": "J.Lane", "statId": 11, "yards": 1, "gameId": "2012093007"}, {"sequence": 2, "clubcode": "MIA", "playerName": "J.Lane", "statId": 10, "yards": 0, "gameId": "2012093007"}, {"sequence": 2, "clubcode": "MIA", "playerName": "J.Lane", "statId": 104, "yards": 0, "gameId": "2012093007"}, {"sequence": 1, "clubcode": "TB", "playerName": "J.Lane", "statId": 10, "yards": 0, "gameId": "2015091311"}, {"sequence": 2, "clubcode": "TB", "playerName": "J.Lane", "statId": 115, "yards": 0, "gameId": "2014082300"}, {"sequence": 2, "clubcode": "TB", "playerName": "J.Lane", "statId": 115, "yards": 0, "gameId": "2014082300"}, {"sequence": 5, "clubcode": "TB", "playerName": "J.Lane", "statId": 21, "yards": 1, "gameId": "2014082300"}, {"sequence": 6, "clubcode": "TB", "playerName": "J.Lane", "statId": 113, "yards": 2, "gameId": "2014082300"}, {"sequence": 1, "clubcode": "MIA", "playerName": "J.Lane", "statId": 113, "yards": 23, "gameId": "2012090903"}, {"sequence": 3, "clubcode": "MIA", "playerName": "J.Lane", "statId": 21, "yards": 24, "gameId": "2012090903"}, {"sequence": 7, "clubcode": "MIA", "playerName": "J.Lane", "statId": 115, "yards": 0, "gameId": "2012090903"}, {"sequence": 2, "clubcode": "MIA", "playerName": "J.Lane", "statId": 45, "yards": 18, "gameId": "2012090903"}, {"sequence": 3, "clubcode": "MIA", "playerName": "J.Lane", "statId": 21, "yards": 8, "gameId": "2012123001"}, {"sequence": 4, "clubcode": "MIA", "playerName": "J.Lane", "statId": 115, "yards": 0, "gameId": "2012123001"}, {"sequence": 5, "clubcode": "MIA", "playerName": "J.Lane", "statId": 113, "yards": 9, "gameId": "2012123001"}, {"sequence": 3, "clubcode": "MIA", "playerName": "J.Lane", "statId": 21, "yards": 6, "gameId": "2012123001"}, {"sequence": 4, "clubcode": "MIA", "playerName": "J.Lane", "statId": 115, "yards": 0, "gameId": "2012123001"}, {"sequence": 5, "clubcode": "MIA", "playerName": "J.Lane", "statId": 113, "yards": 6, "gameId": "2012123001"}, {"sequence": 2, "clubcode": "TB", "playerName": "J.Lane", "statId": 45, "yards": 9, "gameId": "2014111608"}, {"sequence": 1, "clubcode": "MIA", "playerName": "J.Lane", "statId": 115, "yards": 0, "gameId": "2012082452"}, {"sequence": 3, "clubcode": "MIA", "playerName": "J.Lane", "statId": 113, "yards": 6, "gameId": "2012082452"}, {"sequence": 5, "clubcode": "MIA", "playerName": "J.Lane", "statId": 21, "yards": 10, "gameId": "2012082452"}, {"sequence": 1, "clubcode": "MIA", "playerName": "J.Lane", "statId": 10, "yards": 1, "gameId": "2012082452"}, {"sequence": 3, "clubcode": "TB", "playerName": "J.Lane", "statId": 21, "yards": 8, "gameId": "2015111502"}, {"sequence": 4, "clubcode": "TB", "playerName": "J.Lane", "statId": 115, "yards": 0, "gameId": "2015111502"}, {"sequence": 5, "clubcode": "TB", "playerName": "J.Lane", "statId": 113, "yards": 10, "gameId": "2015111502"}, {"sequence": 1, "clubcode": "MIA", "playerName": "J.Lane", "statId": 10, "yards": 0, "gameId": "2012111500"}, {"sequence": 1, "clubcode": "TB", "playerName": "J.Lane", "statId": 10, "yards": 2, "gameId": "2014092807"}, {"sequence": 2, "clubcode": "MIA", "playerName": "J.Lane", "statId": 115, "yards": 0, "gameId": "2012110407"}, {"sequence": 4, "clubcode": "TB", "playerName": "J.Lane", "statId": 21, "yards": 14, "gameId": "2014081604"}, {"sequence": 5, "clubcode": "TB", "playerName": "J.Lane", "statId": 115, "yards": 0, "gameId": "2014081604"}, {"sequence": 6, "clubcode": "TB", "playerName": "J.Lane", "statId": 113, "yards": 15, "gameId": "2014081604"}, {"sequence": 3, "clubcode": "TB", "playerName": "J.Lane", "statId": 21, "yards": 5, "gameId": "2015110807"}, {"sequence": 4, "clubcode": "TB", "playerName": "J.Lane", "statId": 115, "yards": 0, "gameId": "2015110807"}, {"sequence": 5, "clubcode": "TB", "playerName": "J.Lane", "statId": 113, "yards": 1, "gameId": "2015110807"}, {"sequence": 2, "clubcode": "MIA", "playerName": "J.Lane", "statId": 45, "yards": 11, "gameId": "2013081703"}, {"sequence": 3, "clubcode": "TB", "playerName": "J.Lane", "statId": 21, "yards": 7, "gameId": "2015082451"}, {"sequence": 4, "clubcode": "TB", "playerName": "J.Lane", "statId": 115, "yards": 0, "gameId": "2015082451"}, {"sequence": 5, "clubcode": "TB", "playerName": "J.Lane", "statId": 113, "yards": 5, "gameId": "2015082451"}, {"sequence": 1, "clubcode": "TB", "playerName": "J.Lane", "statId": 10, "yards": 2, "gameId": "2014112302"}, {"sequence": 7, "clubcode": "TB", "playerName": "J.Lane", "statId": 55, "yards": 0, "gameId": "2015112204"}, {"sequence": 3, "clubcode": "TB", "playerName": "J.Lane", "statId": 21, "yards": 3, "gameId": "2014091409"}, {"sequence": 5, "clubcode": "TB", "playerName": "J.Lane", "statId": 113, "yards": 2, "gameId": "2014091409"}, {"sequence": 6, "clubcode": "TB", "playerName": "J.Lane", "statId": 115, "yards": 0, "gameId": "2014091409"}, {"sequence": 2, "clubcode": "MIA", "playerName": "J.Lane", "statId": 115, "yards": 0, "gameId": "2013082403"}], "totals": {"52": {"statId": 52, "count": 3, "totYds": 0}, "55": {"statId": 55, "count": 3, "totYds": 0}, "21": {"statId": 21, "count": 18, "totYds": 135}, "115": {"statId": 115, "count": 22, "totYds": 0}, "113": {"statId": 113, "count": 19, "totYds": 110}, "10": {"statId": 10, "count": 18, "totYds": 72}, "22": {"statId": 22, "count": 1, "totYds": 4}, "93": {"statId": 93, "count": 1, "totYds": 5}, "82": {"statId": 82, "count": 1, "totYds": 0}, "106": {"statId": 106, "count": 1, "totYds": 0}, "79": {"statId": 79, "count": 2, "totYds": 0}, "11": {"statId": 11, "count": 2, "totYds": 2}, "45": {"statId": 45, "count": 4, "totYds": 62}, "104": {"statId": 104, "count": 1, "totYds": 0}}, "playerName": "J.Lane"}