{"teams": ["WAS"], "stats": [{"sequence": 4, "clubcode": "WAS", "playerName": "D.Scott", "statId": 79, "yards": 0, "gameId": "2012080951"}, {"sequence": 3, "clubcode": "WAS", "playerName": "D.Scott", "statId": 82, "yards": 0, "gameId": "2012080951"}, {"sequence": 2, "clubcode": "WAS", "playerName": "D.Scott", "statId": 79, "yards": 0, "gameId": "2012080951"}, {"sequence": 2, "clubcode": "WAS", "playerName": "D.Scott", "statId": 79, "yards": 0, "gameId": "2011081253"}, {"sequence": 5, "clubcode": "WAS", "playerName": "D.Scott", "statId": 110, "yards": 0, "gameId": "2011081253"}, {"sequence": 4, "clubcode": "WAS", "playerName": "D.Scott", "statId": 80, "yards": 0, "gameId": "2010082151"}, {"sequence": 2, "clubcode": "WAS", "playerName": "D.Scott", "statId": 80, "yards": 0, "gameId": "2010082151"}, {"sequence": 2, "clubcode": "WAS", "playerName": "D.Scott", "statId": 80, "yards": 0, "gameId": "2010082151"}, {"sequence": 3, "clubcode": "WAS", "playerName": "D.Scott", "statId": 79, "yards": 0, "gameId": "2012010107"}, {"sequence": 4, "clubcode": "WAS", "playerName": "D.Scott", "statId": 120, "yards": 0, "gameId": "2012010107"}, {"sequence": 8, "clubcode": "WAS", "playerName": "D.Scott", "statId": 110, "yards": 0, "gameId": "2011121803"}, {"sequence": 2, "clubcode": "WAS", "playerName": "D.Scott", "statId": 82, "yards": 0, "gameId": "2012082952"}, {"sequence": 1, "clubcode": "WAS", "playerName": "D.Scott", "statId": 402, "yards": 1, "gameId": "2012082952"}, {"sequence": 3, "clubcode": "WAS", "playerName": "D.Scott", "statId": 79, "yards": 0, "gameId": "2012082952"}, {"sequence": 4, "clubcode": "WAS", "playerName": "D.Scott", "statId": 120, "yards": 0, "gameId": "2012082952"}, {"sequence": 3, "clubcode": "WAS", "playerName": "D.Scott", "statId": 82, "yards": 0, "gameId": "2012082952"}, {"sequence": 1, "clubcode": "WAS", "playerName": "D.Scott", "statId": 402, "yards": 8, "gameId": "2012082952"}, {"sequence": 3, "clubcode": "WAS", "playerName": "D.Scott", "statId": 79, "yards": 0, "gameId": "2012082952"}, {"sequence": 4, "clubcode": "WAS", "playerName": "D.Scott", "statId": 110, "yards": 0, "gameId": "2012082952"}, {"sequence": 5, "clubcode": "WAS", "playerName": "D.Scott", "statId": 83, "yards": -8, "gameId": "2012082952"}, {"sequence": 6, "clubcode": "WAS", "playerName": "D.Scott", "statId": 120, "yards": 0, "gameId": "2012082952"}, {"sequence": 1, "clubcode": "WAS", "playerName": "D.Scott", "statId": 110, "yards": 0, "gameId": "2012082952"}, {"sequence": 3, "clubcode": "WAS", "playerName": "D.Scott", "statId": 82, "yards": 0, "gameId": "2011090159"}, {"sequence": 2, "clubcode": "WAS", "playerName": "D.Scott", "statId": 82, "yards": 0, "gameId": "2011090159"}, {"sequence": 3, "clubcode": "WAS", "playerName": "D.Scott", "statId": 82, "yards": 0, "gameId": "2010090266"}, {"sequence": 2, "clubcode": "WAS", "playerName": "D.Scott", "statId": 80, "yards": 0, "gameId": "2010090266"}, {"sequence": 2, "clubcode": "WAS", "playerName": "D.Scott", "statId": 83, "yards": -3, "gameId": "2010090266"}, {"sequence": 3, "clubcode": "WAS", "playerName": "D.Scott", "statId": 110, "yards": 0, "gameId": "2010090266"}, {"sequence": 4, "clubcode": "WAS", "playerName": "D.Scott", "statId": 79, "yards": 0, "gameId": "2010090266"}, {"sequence": 5, "clubcode": "WAS", "playerName": "D.Scott", "statId": 120, "yards": 0, "gameId": "2010090266"}, {"sequence": 2, "clubcode": "WAS", "playerName": "D.Scott", "statId": 79, "yards": 0, "gameId": "2010090266"}, {"sequence": 1, "clubcode": "WAS", "playerName": "D.Scott", "statId": 82, "yards": 0, "gameId": "2011112707"}, {"sequence": 2, "clubcode": "WAS", "playerName": "D.Scott", "statId": 82, "yards": 0, "gameId": "2011081951"}, {"sequence": 2, "clubcode": "WAS", "playerName": "D.Scott", "statId": 79, "yards": 0, "gameId": "2011081951"}, {"sequence": 3, "clubcode": "WAS", "playerName": "D.Scott", "statId": 82, "yards": 0, "gameId": "2011081951"}, {"sequence": 2, "clubcode": "WAS", "playerName": "D.Scott", "statId": 110, "yards": 0, "gameId": "2011081951"}, {"sequence": 3, "clubcode": "WAS", "playerName": "D.Scott", "statId": 79, "yards": 0, "gameId": "2011081951"}, {"sequence": 4, "clubcode": "WAS", "playerName": "D.Scott", "statId": 83, "yards": -6, "gameId": "2011081951"}, {"sequence": 5, "clubcode": "WAS", "playerName": "D.Scott", "statId": 120, "yards": 0, "gameId": "2011081951"}, {"sequence": 3, "clubcode": "WAS", "playerName": "D.Scott", "statId": 82, "yards": 0, "gameId": "2011081951"}, {"sequence": 2, "clubcode": "WAS", "playerName": "D.Scott", "statId": 83, "yards": -5, "gameId": "2010082753"}, {"sequence": 3, "clubcode": "WAS", "playerName": "D.Scott", "statId": 79, "yards": 0, "gameId": "2010082753"}, {"sequence": 6, "clubcode": "WAS", "playerName": "D.Scott", "statId": 91, "yards": 0, "gameId": "2010082753"}, {"sequence": 2, "clubcode": "WAS", "playerName": "D.Scott", "statId": 82, "yards": 0, "gameId": "2011112005"}, {"sequence": 2, "clubcode": "WAS", "playerName": "D.Scott", "statId": 80, "yards": 0, "gameId": "2011122406"}, {"sequence": 3, "clubcode": "WAS", "playerName": "D.Scott", "statId": 110, "yards": 0, "gameId": "2011010208"}, {"sequence": 1, "clubcode": "WAS", "playerName": "D.Scott", "statId": 82, "yards": 0, "gameId": "2011010208"}, {"sequence": 2, "clubcode": "WAS", "playerName": "D.Scott", "statId": 79, "yards": 0, "gameId": "2011010208"}, {"sequence": 4, "clubcode": "WAS", "playerName": "D.Scott", "statId": 110, "yards": 0, "gameId": "2012082551"}, {"sequence": 2, "clubcode": "WAS", "playerName": "D.Scott", "statId": 79, "yards": 0, "gameId": "2012081852"}, {"sequence": 2, "clubcode": "WAS", "playerName": "D.Scott", "statId": 79, "yards": 0, "gameId": "2012081852"}, {"sequence": 2, "clubcode": "WAS", "playerName": "D.Scott", "statId": 79, "yards": 0, "gameId": "2010081351"}, {"sequence": 3, "clubcode": "WAS", "playerName": "D.Scott", "statId": 80, "yards": 0, "gameId": "2010081351"}, {"sequence": 5, "clubcode": "WAS", "playerName": "D.Scott", "statId": 120, "yards": 0, "gameId": "2010081351"}], "playerName": "D.Scott"}