{"teams": ["JAC", "DEN"], "stats": [{"sequence": 4, "clubcode": "JAC", "playerName": "L.Thomas", "statId": 21, "yards": 8, "gameId": "2014080802"}, {"sequence": 5, "clubcode": "JAC", "playerName": "L.Thomas", "statId": 115, "yards": 0, "gameId": "2014080802"}, {"sequence": 6, "clubcode": "JAC", "playerName": "L.Thomas", "statId": 113, "yards": 2, "gameId": "2014080802"}, {"sequence": 5, "clubcode": "JAC", "playerName": "L.Thomas", "statId": 21, "yards": 6, "gameId": "2014080802"}, {"sequence": 6, "clubcode": "JAC", "playerName": "L.Thomas", "statId": 115, "yards": 0, "gameId": "2014080802"}, {"sequence": 7, "clubcode": "JAC", "playerName": "L.Thomas", "statId": 113, "yards": 0, "gameId": "2014080802"}, {"sequence": 6, "clubcode": "JAC", "playerName": "L.Thomas", "statId": 21, "yards": 7, "gameId": "2014080802"}, {"sequence": 7, "clubcode": "JAC", "playerName": "L.Thomas", "statId": 115, "yards": 0, "gameId": "2014080802"}, {"sequence": 8, "clubcode": "JAC", "playerName": "L.Thomas", "statId": 113, "yards": 2, "gameId": "2014080802"}, {"sequence": 2, "clubcode": "JAC", "playerName": "L.Thomas", "statId": 115, "yards": 0, "gameId": "2013122904"}, {"sequence": 3, "clubcode": "JAC", "playerName": "L.Thomas", "statId": 21, "yards": 18, "gameId": "2013122904"}, {"sequence": 5, "clubcode": "JAC", "playerName": "L.Thomas", "statId": 113, "yards": 13, "gameId": "2013122904"}, {"sequence": 7, "clubcode": "JAC", "playerName": "L.Thomas", "statId": 115, "yards": 0, "gameId": "2013122904"}, {"sequence": 2, "clubcode": "JAC", "playerName": "L.Thomas", "statId": 115, "yards": 0, "gameId": "2013122204"}, {"sequence": 4, "clubcode": "JAC", "playerName": "L.Thomas", "statId": 21, "yards": 13, "gameId": "2013122204"}, {"sequence": 7, "clubcode": "JAC", "playerName": "L.Thomas", "statId": 113, "yards": 5, "gameId": "2013122204"}, {"sequence": 2, "clubcode": "DEN", "playerName": "L.Thomas", "statId": 45, "yards": 34, "gameId": "2013082913"}, {"sequence": 1, "clubcode": "DEN", "playerName": "L.Thomas", "statId": 115, "yards": 0, "gameId": "2013082913"}, {"sequence": 2, "clubcode": "DEN", "playerName": "L.Thomas", "statId": 21, "yards": 14, "gameId": "2013082913"}, {"sequence": 3, "clubcode": "DEN", "playerName": "L.Thomas", "statId": 113, "yards": 0, "gameId": "2013082913"}, {"sequence": 5, "clubcode": "DEN", "playerName": "L.Thomas", "statId": 115, "yards": 0, "gameId": "2013082913"}, {"sequence": 4, "clubcode": "DEN", "playerName": "L.Thomas", "statId": 115, "yards": 0, "gameId": "2013082913"}, {"sequence": 2, "clubcode": "DEN", "playerName": "L.Thomas", "statId": 115, "yards": 0, "gameId": "2013082913"}, {"sequence": 3, "clubcode": "JAC", "playerName": "L.Thomas", "statId": 21, "yards": 6, "gameId": "2014082200"}, {"sequence": 4, "clubcode": "JAC", "playerName": "L.Thomas", "statId": 115, "yards": 0, "gameId": "2014082200"}, {"sequence": 5, "clubcode": "JAC", "playerName": "L.Thomas", "statId": 113, "yards": 0, "gameId": "2014082200"}, {"sequence": 3, "clubcode": "JAC", "playerName": "L.Thomas", "statId": 21, "yards": 7, "gameId": "2014082200"}, {"sequence": 4, "clubcode": "JAC", "playerName": "L.Thomas", "statId": 115, "yards": 0, "gameId": "2014082200"}, {"sequence": 5, "clubcode": "JAC", "playerName": "L.Thomas", "statId": 113, "yards": 3, "gameId": "2014082200"}, {"sequence": 4, "clubcode": "DEN", "playerName": "L.Thomas", "statId": 21, "yards": 14, "gameId": "2013080804"}, {"sequence": 5, "clubcode": "DEN", "playerName": "L.Thomas", "statId": 115, "yards": 0, "gameId": "2013080804"}, {"sequence": 6, "clubcode": "DEN", "playerName": "L.Thomas", "statId": 113, "yards": 16, "gameId": "2013080804"}, {"sequence": 2, "clubcode": "DEN", "playerName": "L.Thomas", "statId": 115, "yards": 0, "gameId": "2013080804"}, {"sequence": 1, "clubcode": "DEN", "playerName": "L.Thomas", "statId": 93, "yards": 9, "gameId": "2013082407"}, {"sequence": 4, "clubcode": "DEN", "playerName": "L.Thomas", "statId": 21, "yards": 6, "gameId": "2013082407"}, {"sequence": 5, "clubcode": "DEN", "playerName": "L.Thomas", "statId": 115, "yards": 0, "gameId": "2013082407"}, {"sequence": 6, "clubcode": "DEN", "playerName": "L.Thomas", "statId": 113, "yards": 6, "gameId": "2013082407"}, {"sequence": 2, "clubcode": "DEN", "playerName": "L.Thomas", "statId": 115, "yards": 0, "gameId": "2013082407"}, {"sequence": 2, "clubcode": "DEN", "playerName": "L.Thomas", "statId": 115, "yards": 0, "gameId": "2013082407"}], "totals": {"21": {"statId": 21, "count": 10, "totYds": 99}, "115": {"statId": 115, "count": 17, "totYds": 0}, "113": {"statId": 113, "count": 10, "totYds": 47}, "45": {"statId": 45, "count": 1, "totYds": 34}, "93": {"statId": 93, "count": 1, "totYds": 9}}, "playerName": "L.Thomas"}