{"teams": ["BAL"], "stats": [{"sequence": 7, "clubcode": "BAL", "playerName": "W.VanDeSteeg", "statId": 79, "yards": 0, "gameId": "2009082450"}, {"sequence": 2, "clubcode": "BAL", "playerName": "W.VanDeSteeg", "statId": 82, "yards": 0, "gameId": "2009081352"}, {"sequence": 3, "clubcode": "BAL", "playerName": "W.VanDeSteeg", "statId": 79, "yards": 0, "gameId": "2009090352"}, {"sequence": 4, "clubcode": "BAL", "playerName": "W.VanDeSteeg", "statId": 120, "yards": 0, "gameId": "2009090352"}], "playerName": "W.VanDeSteeg"}