{"teams": ["BUF"], "stats": [{"sequence": 3, "clubcode": "BUF", "playerName": "C.Harris", "statId": 79, "yards": 0, "gameId": "2009122700"}, {"sequence": 4, "clubcode": "BUF", "playerName": "C.Harris", "statId": 79, "yards": 0, "gameId": "2010101000"}, {"sequence": 5, "clubcode": "BUF", "playerName": "C.Harris", "statId": 91, "yards": 0, "gameId": "2010101000"}, {"sequence": 3, "clubcode": "BUF", "playerName": "C.Harris", "statId": 79, "yards": 0, "gameId": "2009112204"}, {"sequence": 3, "clubcode": "BUF", "playerName": "C.Harris", "statId": 79, "yards": 0, "gameId": "2009081551"}, {"sequence": 5, "clubcode": "BUF", "playerName": "C.Harris", "statId": 25, "yards": 7, "gameId": "2010010300"}, {"sequence": 6, "clubcode": "BUF", "playerName": "C.Harris", "statId": 85, "yards": 0, "gameId": "2010010300"}, {"sequence": 9, "clubcode": "BUF", "playerName": "C.Harris", "statId": 82, "yards": 0, "gameId": "2010010300"}, {"sequence": 8, "clubcode": "BUF", "playerName": "C.Harris", "statId": 79, "yards": 0, "gameId": "2010010300"}, {"sequence": 4, "clubcode": "BUF", "playerName": "C.Harris", "statId": 25, "yards": 0, "gameId": "2010010300"}, {"sequence": 5, "clubcode": "BUF", "playerName": "C.Harris", "statId": 85, "yards": 0, "gameId": "2010010300"}, {"sequence": 3, "clubcode": "BUF", "playerName": "C.Harris", "statId": 79, "yards": 0, "gameId": "2009090350"}, {"sequence": 3, "clubcode": "BUF", "playerName": "C.Harris", "statId": 79, "yards": 0, "gameId": "2009112901"}, {"sequence": 2, "clubcode": "BUF", "playerName": "Ca.Harris", "statId": 82, "yards": 0, "gameId": "2010090251"}, {"sequence": 2, "clubcode": "BUF", "playerName": "Ca.Harris", "statId": 79, "yards": 0, "gameId": "2010090251"}, {"sequence": 6, "clubcode": "BUF", "playerName": "C.Harris", "statId": 79, "yards": 0, "gameId": "2009082254"}, {"sequence": 6, "clubcode": "BUF", "playerName": "C.Harris", "statId": 79, "yards": 0, "gameId": "2009082254"}, {"sequence": 3, "clubcode": "BUF", "playerName": "C.Harris", "statId": 79, "yards": 0, "gameId": "2010081351"}, {"sequence": 2, "clubcode": "BUF", "playerName": "C.Harris", "statId": 80, "yards": 0, "gameId": "2010081351"}, {"sequence": 3, "clubcode": "BUF", "playerName": "C.Harris", "statId": 82, "yards": 0, "gameId": "2010081351"}, {"sequence": 2, "clubcode": "BUF", "playerName": "C.Harris", "statId": 80, "yards": 0, "gameId": "2010081351"}, {"sequence": 4, "clubcode": "BUF", "playerName": "C.Harris", "statId": 82, "yards": 0, "gameId": "2010081351"}, {"sequence": 3, "clubcode": "BUF", "playerName": "C.Harris", "statId": 79, "yards": 0, "gameId": "2010081351"}, {"sequence": 2, "clubcode": "BUF", "playerName": "C.Harris", "statId": 79, "yards": 0, "gameId": "2010081351"}, {"sequence": 3, "clubcode": "BUF", "playerName": "C.Harris", "statId": 80, "yards": 0, "gameId": "2010081952"}, {"sequence": 5, "clubcode": "BUF", "playerName": "C.Harris", "statId": 120, "yards": 0, "gameId": "2010081952"}], "playerName": "C.Harris"}