{"teams": ["KC"], "stats": [{"sequence": 3, "clubcode": "KC", "playerName": "D.Walker", "statId": 79, "yards": 0, "gameId": "2014082803"}, {"sequence": 4, "clubcode": "KC", "playerName": "D.Walker", "statId": 120, "yards": 0, "gameId": "2014082803"}, {"sequence": 5, "clubcode": "KC", "playerName": "D.Walker", "statId": 402, "yards": 1, "gameId": "2014082803"}], "totals": {"79": {"statId": 79, "count": 1, "totYds": 0}, "120": {"statId": 120, "count": 1, "totYds": 0}, "402": {"statId": 402, "count": 1, "totYds": 1}}, "playerName": "D.Walker"}