{"teams": ["CHI"], "stats": [{"sequence": 5, "clubcode": "CHI", "playerName": "D.McClover", "statId": 93, "yards": 5, "gameId": "2009121302"}, {"sequence": 3, "clubcode": "CHI", "playerName": "D.McClover", "statId": 79, "yards": 0, "gameId": "2009110801"}, {"sequence": 4, "clubcode": "CHI", "playerName": "D.McClover", "statId": 79, "yards": 0, "gameId": "2009110801"}, {"sequence": 3, "clubcode": "CHI", "playerName": "D.McClover", "statId": 79, "yards": 0, "gameId": "2009120602"}, {"sequence": 3, "clubcode": "CHI", "playerName": "D.McClover", "statId": 79, "yards": 0, "gameId": "2009110102"}, {"sequence": 4, "clubcode": "CHI", "playerName": "D.McClover", "statId": 82, "yards": 0, "gameId": "2009100400"}, {"sequence": 3, "clubcode": "CHI", "playerName": "D.McClover", "statId": 79, "yards": 0, "gameId": "2009100400"}, {"sequence": 3, "clubcode": "CHI", "playerName": "D.McClover", "statId": 79, "yards": 0, "gameId": "2009112213"}, {"sequence": 3, "clubcode": "CHI", "playerName": "D.McClover", "statId": 82, "yards": 0, "gameId": "2009102500"}, {"sequence": 4, "clubcode": "CHI", "playerName": "D.McClover", "statId": 82, "yards": 0, "gameId": "2009102500"}, {"sequence": 3, "clubcode": "CHI", "playerName": "D.McClover", "statId": 79, "yards": 0, "gameId": "2010010304"}, {"sequence": 3, "clubcode": "CHI", "playerName": "D.McClover", "statId": 80, "yards": 0, "gameId": "2009122800"}, {"sequence": 7, "clubcode": "CHI", "playerName": "D.McClover", "statId": 79, "yards": 0, "gameId": "2009090356"}, {"sequence": 3, "clubcode": "CHI", "playerName": "D.McClover", "statId": 79, "yards": 0, "gameId": "2009090356"}, {"sequence": 3, "clubcode": "CHI", "playerName": "D.McClover", "statId": 110, "yards": 0, "gameId": "2009090356"}], "playerName": "D.McClover"}