{"teams": ["STL"], "stats": [{"sequence": 3, "clubcode": "STL", "playerName": "A.Franklin", "statId": 45, "yards": 27, "gameId": "2014080805"}, {"sequence": 3, "clubcode": "STL", "playerName": "A.Franklin", "statId": 115, "yards": 0, "gameId": "2014080805"}, {"sequence": 6, "clubcode": "STL", "playerName": "A.Franklin", "statId": 22, "yards": 15, "gameId": "2014080805"}, {"sequence": 7, "clubcode": "STL", "playerName": "A.Franklin", "statId": 113, "yards": 15, "gameId": "2014080805"}, {"sequence": 2, "clubcode": "STL", "playerName": "A.Franklin", "statId": 45, "yards": 15, "gameId": "2014082303"}, {"sequence": 4, "clubcode": "STL", "playerName": "A.Franklin", "statId": 21, "yards": 10, "gameId": "2014082804"}, {"sequence": 5, "clubcode": "STL", "playerName": "A.Franklin", "statId": 115, "yards": 0, "gameId": "2014082804"}, {"sequence": 6, "clubcode": "STL", "playerName": "A.Franklin", "statId": 113, "yards": 8, "gameId": "2014082804"}, {"sequence": 1, "clubcode": "STL", "playerName": "A.Franklin", "statId": 93, "yards": 10, "gameId": "2014082804"}, {"sequence": 3, "clubcode": "STL", "playerName": "A.Franklin", "statId": 115, "yards": 0, "gameId": "2014082804"}, {"sequence": 2, "clubcode": "STL", "playerName": "A.Franklin", "statId": 45, "yards": 25, "gameId": "2014081600"}, {"sequence": 3, "clubcode": "STL", "playerName": "A.Franklin", "statId": 115, "yards": 0, "gameId": "2014081600"}, {"sequence": 2, "clubcode": "STL", "playerName": "A.Franklin", "statId": 45, "yards": 18, "gameId": "2014081600"}], "totals": {"45": {"statId": 45, "count": 4, "totYds": 85}, "115": {"statId": 115, "count": 4, "totYds": 0}, "22": {"statId": 22, "count": 1, "totYds": 15}, "113": {"statId": 113, "count": 2, "totYds": 23}, "21": {"statId": 21, "count": 1, "totYds": 10}, "93": {"statId": 93, "count": 1, "totYds": 10}}, "playerName": "A.Franklin"}