{"teams": ["NYG", "TB", "WAS", "IND", "DET", "DEN"], "stats": [{"sequence": 3, "clubcode": "NYG", "playerName": "D.Johnson", "statId": 79, "yards": 0, "gameId": "2010092600"}, {"sequence": 3, "clubcode": "TB", "playerName": "D.Johnson", "statId": 85, "yards": 0, "gameId": "2011081851"}, {"sequence": 4, "clubcode": "TB", "playerName": "D.Johnson", "statId": 82, "yards": 0, "gameId": "2011081851"}, {"sequence": 6, "clubcode": "TB", "playerName": "D.Johnson", "statId": 79, "yards": 0, "gameId": "2011081851"}, {"sequence": 3, "clubcode": "TB", "playerName": "D.Johnson", "statId": 79, "yards": 0, "gameId": "2011081851"}, {"sequence": 6, "clubcode": "TB", "playerName": "D.Johnson", "statId": 79, "yards": 0, "gameId": "2011081851"}, {"sequence": 2, "clubcode": "WAS", "playerName": "D.Johnson", "statId": 79, "yards": 0, "gameId": "2012111800"}, {"sequence": 6, "clubcode": "WAS", "playerName": "D.Johnson", "statId": 79, "yards": 0, "gameId": "2012111800"}, {"sequence": 2, "clubcode": "NYG", "playerName": "D.Johnson", "statId": 82, "yards": 0, "gameId": "2010082855"}, {"sequence": 1, "clubcode": "NYG", "playerName": "D.Johnson", "statId": 79, "yards": 0, "gameId": "2010082855"}, {"sequence": 3, "clubcode": "NYG", "playerName": "D.Johnson", "statId": 80, "yards": 0, "gameId": "2010091206"}, {"sequence": 3, "clubcode": "NYG", "playerName": "D.Johnson", "statId": 80, "yards": 0, "gameId": "2010091206"}, {"sequence": 1, "clubcode": "IND", "playerName": "D.Johnson", "statId": 79, "yards": 0, "gameId": "2012081251"}, {"sequence": 2, "clubcode": "IND", "playerName": "D.Johnson", "statId": 79, "yards": 0, "gameId": "2012081251"}, {"sequence": 7, "clubcode": "IND", "playerName": "D.Johnson", "statId": 79, "yards": 0, "gameId": "2012081251"}, {"sequence": 6, "clubcode": "IND", "playerName": "D.Johnson", "statId": 79, "yards": 0, "gameId": "2012081251"}, {"sequence": 4, "clubcode": "IND", "playerName": "D.Johnson", "statId": 82, "yards": 0, "gameId": "2012081251"}, {"sequence": 3, "clubcode": "NYG", "playerName": "D.Johnson", "statId": 82, "yards": 0, "gameId": "2010082152"}, {"sequence": 8, "clubcode": "NYG", "playerName": "D.Johnson", "statId": 79, "yards": 0, "gameId": "2010082152"}, {"sequence": 7, "clubcode": "NYG", "playerName": "D.Johnson", "statId": 79, "yards": 0, "gameId": "2010082152"}, {"sequence": 5, "clubcode": "NYG", "playerName": "D.Johnson", "statId": 79, "yards": 0, "gameId": "2010082152"}, {"sequence": 3, "clubcode": "WAS", "playerName": "D.Johnson", "statId": 79, "yards": 0, "gameId": "2012121604"}, {"sequence": 7, "clubcode": "IND", "playerName": "D.Johnson", "statId": 82, "yards": 0, "gameId": "2012081951"}, {"sequence": 7, "clubcode": "IND", "playerName": "D.Johnson", "statId": 79, "yards": 0, "gameId": "2012081951"}, {"sequence": 4, "clubcode": "NYG", "playerName": "D.J.Johnson", "statId": 79, "yards": 0, "gameId": "2009122100"}, {"sequence": 3, "clubcode": "NYG", "playerName": "D.J.Johnson", "statId": 79, "yards": 0, "gameId": "2009122100"}, {"sequence": 6, "clubcode": "DET", "playerName": "D.Johnson", "statId": 79, "yards": 0, "gameId": "2013081502"}, {"sequence": 2, "clubcode": "NYG", "playerName": "D.Johnson", "statId": 79, "yards": 0, "gameId": "2010091914"}, {"sequence": 3, "clubcode": "DEN", "playerName": "D.Johnson", "statId": 79, "yards": 0, "gameId": "2009090361"}, {"sequence": 3, "clubcode": "DEN", "playerName": "D.Johnson", "statId": 85, "yards": 0, "gameId": "2009090361"}, {"sequence": 2, "clubcode": "DEN", "playerName": "D.Johnson", "statId": 79, "yards": 0, "gameId": "2009090361"}, {"sequence": 3, "clubcode": "DEN", "playerName": "D.Johnson", "statId": 79, "yards": 0, "gameId": "2009090361"}, {"sequence": 4, "clubcode": "DEN", "playerName": "D.Johnson", "statId": 120, "yards": 0, "gameId": "2009090361"}, {"sequence": 2, "clubcode": "DEN", "playerName": "D.Johnson", "statId": 80, "yards": 0, "gameId": "2009090361"}, {"sequence": 8, "clubcode": "DEN", "playerName": "D.Johnson", "statId": 79, "yards": 0, "gameId": "2009090361"}, {"sequence": 7, "clubcode": "DEN", "playerName": "D.Johnson", "statId": 79, "yards": 0, "gameId": "2009090361"}, {"sequence": 2, "clubcode": "DEN", "playerName": "D.Johnson", "statId": 79, "yards": 0, "gameId": "2009083050"}, {"sequence": 3, "clubcode": "DEN", "playerName": "D.Johnson", "statId": 79, "yards": 0, "gameId": "2009083050"}, {"sequence": 2, "clubcode": "DEN", "playerName": "D.Johnson", "statId": 79, "yards": 0, "gameId": "2009082259"}, {"sequence": 4, "clubcode": "WAS", "playerName": "D.Johnson", "statId": 79, "yards": 0, "gameId": "2012120900"}, {"sequence": 2, "clubcode": "WAS", "playerName": "D.Johnson", "statId": 79, "yards": 0, "gameId": "2012120900"}, {"sequence": 1, "clubcode": "WAS", "playerName": "D.Johnson", "statId": 82, "yards": 0, "gameId": "2012120900"}, {"sequence": 3, "clubcode": "IND", "playerName": "D.Johnson", "statId": 79, "yards": 0, "gameId": "2012082551"}, {"sequence": 5, "clubcode": "IND", "playerName": "D.Johnson", "statId": 79, "yards": 0, "gameId": "2012082551"}, {"sequence": 4, "clubcode": "IND", "playerName": "D.Johnson", "statId": 79, "yards": 0, "gameId": "2012082551"}, {"sequence": 3, "clubcode": "WAS", "playerName": "D.Johnson", "statId": 79, "yards": 0, "gameId": "2012112201"}, {"sequence": 3, "clubcode": "DET", "playerName": "D.Johnson", "statId": 79, "yards": 0, "gameId": "2013080901"}, {"sequence": 3, "clubcode": "DET", "playerName": "D.Johnson", "statId": 82, "yards": 0, "gameId": "2013080901"}, {"sequence": 3, "clubcode": "DET", "playerName": "D.Johnson", "statId": 79, "yards": 0, "gameId": "2013080901"}, {"sequence": 2, "clubcode": "DET", "playerName": "D.Johnson", "statId": 79, "yards": 0, "gameId": "2013080901"}, {"sequence": 7, "clubcode": "DET", "playerName": "D.Johnson", "statId": 82, "yards": 0, "gameId": "2013080901"}, {"sequence": 2, "clubcode": "DET", "playerName": "D.Johnson", "statId": 82, "yards": 0, "gameId": "2013080901"}, {"sequence": 2, "clubcode": "DET", "playerName": "D.Johnson", "statId": 93, "yards": 8, "gameId": "2013080901"}, {"sequence": 5, "clubcode": "DET", "playerName": "D.Johnson", "statId": 79, "yards": 0, "gameId": "2013080901"}, {"sequence": 7, "clubcode": "NYG", "playerName": "D.J.Johnson", "statId": 79, "yards": 0, "gameId": "2010010307"}, {"sequence": 3, "clubcode": "NYG", "playerName": "D.J.Johnson", "statId": 82, "yards": 0, "gameId": "2010010307"}, {"sequence": 8, "clubcode": "NYG", "playerName": "D.J.Johnson", "statId": 79, "yards": 0, "gameId": "2010010307"}, {"sequence": 3, "clubcode": "WAS", "playerName": "D.Johnson", "statId": 79, "yards": 0, "gameId": "2012122307"}, {"sequence": 4, "clubcode": "NYG", "playerName": "D.J.Johnson", "statId": 82, "yards": 0, "gameId": "2009122705"}, {"sequence": 5, "clubcode": "TB", "playerName": "D.Johnson", "statId": 93, "yards": 10, "gameId": "2011082760"}, {"sequence": 2, "clubcode": "NYG", "playerName": "D.Johnson", "statId": 79, "yards": 0, "gameId": "2010090253"}, {"sequence": 2, "clubcode": "NYG", "playerName": "D.Johnson", "statId": 79, "yards": 0, "gameId": "2010090253"}, {"sequence": 7, "clubcode": "NYG", "playerName": "D.Johnson", "statId": 79, "yards": 0, "gameId": "2010090253"}, {"sequence": 4, "clubcode": "TB", "playerName": "D.Johnson", "statId": 79, "yards": 0, "gameId": "2011081255"}, {"sequence": 3, "clubcode": "TB", "playerName": "D.Johnson", "statId": 85, "yards": 0, "gameId": "2011081255"}, {"sequence": 2, "clubcode": "TB", "playerName": "D.Johnson", "statId": 79, "yards": 0, "gameId": "2011081255"}, {"sequence": 7, "clubcode": "TB", "playerName": "D.Johnson", "statId": 79, "yards": 0, "gameId": "2011081255"}, {"sequence": 6, "clubcode": "TB", "playerName": "D.Johnson", "statId": 25, "yards": 0, "gameId": "2011090159"}, {"sequence": 7, "clubcode": "TB", "playerName": "D.Johnson", "statId": 85, "yards": 0, "gameId": "2011090159"}, {"sequence": 6, "clubcode": "TB", "playerName": "D.Johnson", "statId": 79, "yards": 0, "gameId": "2011090159"}, {"sequence": 7, "clubcode": "TB", "playerName": "D.Johnson", "statId": 82, "yards": 0, "gameId": "2011090159"}, {"sequence": 7, "clubcode": "NYG", "playerName": "D.Johnson", "statId": 79, "yards": 0, "gameId": "2010081651"}, {"sequence": 2, "clubcode": "NYG", "playerName": "D.Johnson", "statId": 79, "yards": 0, "gameId": "2010081651"}, {"sequence": 2, "clubcode": "NYG", "playerName": "D.Johnson", "statId": 79, "yards": 0, "gameId": "2010081651"}, {"sequence": 3, "clubcode": "NYG", "playerName": "D.Johnson", "statId": 82, "yards": 0, "gameId": "2010081651"}, {"sequence": 7, "clubcode": "NYG", "playerName": "D.Johnson", "statId": 79, "yards": 0, "gameId": "2010081651"}, {"sequence": 4, "clubcode": "NYG", "playerName": "D.Johnson", "statId": 25, "yards": 0, "gameId": "2010081651"}, {"sequence": 5, "clubcode": "NYG", "playerName": "D.Johnson", "statId": 85, "yards": 0, "gameId": "2010081651"}, {"sequence": 6, "clubcode": "IND", "playerName": "D.Johnson", "statId": 79, "yards": 0, "gameId": "2012083056"}, {"sequence": 3, "clubcode": "IND", "playerName": "D.Johnson", "statId": 82, "yards": 0, "gameId": "2012083056"}, {"sequence": 2, "clubcode": "IND", "playerName": "D.Johnson", "statId": 79, "yards": 0, "gameId": "2012083056"}, {"sequence": 3, "clubcode": "IND", "playerName": "D.Johnson", "statId": 82, "yards": 0, "gameId": "2012083056"}, {"sequence": 2, "clubcode": "IND", "playerName": "D.Johnson", "statId": 93, "yards": 5, "gameId": "2012083056"}, {"sequence": 2, "clubcode": "IND", "playerName": "D.Johnson", "statId": 79, "yards": 0, "gameId": "2012083056"}, {"sequence": 3, "clubcode": "IND", "playerName": "D.Johnson", "statId": 82, "yards": 0, "gameId": "2012083056"}, {"sequence": 7, "clubcode": "IND", "playerName": "D.Johnson", "statId": 79, "yards": 0, "gameId": "2012083056"}], "totals": {"79": {"statId": 79, "count": 56, "totYds": 0}, "85": {"statId": 85, "count": 5, "totYds": 0}, "82": {"statId": 82, "count": 16, "totYds": 0}, "80": {"statId": 80, "count": 3, "totYds": 0}, "120": {"statId": 120, "count": 1, "totYds": 0}, "93": {"statId": 93, "count": 3, "totYds": 23}, "25": {"statId": 25, "count": 2, "totYds": 0}}, "playerName": "D.Johnson"}