{"teams": ["ATL"], "stats": [{"sequence": 1, "clubcode": "ATL", "playerName": "D.Shockley", "statId": 14, "yards": 0, "gameId": "2009081550"}, {"sequence": 3, "clubcode": "ATL", "playerName": "D.Shockley", "statId": 112, "yards": 5, "gameId": "2009081550"}, {"sequence": 4, "clubcode": "ATL", "playerName": "D.Shockley", "statId": 15, "yards": 10, "gameId": "2009081550"}, {"sequence": 5, "clubcode": "ATL", "playerName": "D.Shockley", "statId": 111, "yards": 8, "gameId": "2009081550"}, {"sequence": 1, "clubcode": "ATL", "playerName": "D.Shockley", "statId": 14, "yards": 0, "gameId": "2009081550"}, {"sequence": 4, "clubcode": "ATL", "playerName": "D.Shockley", "statId": 112, "yards": 13, "gameId": "2009081550"}, {"sequence": 1, "clubcode": "ATL", "playerName": "D.Shockley", "statId": 14, "yards": 0, "gameId": "2009081550"}, {"sequence": 3, "clubcode": "ATL", "playerName": "D.Shockley", "statId": 112, "yards": 14, "gameId": "2009081550"}, {"sequence": 2, "clubcode": "ATL", "playerName": "D.Shockley", "statId": 15, "yards": 6, "gameId": "2009081550"}, {"sequence": 3, "clubcode": "ATL", "playerName": "D.Shockley", "statId": 111, "yards": -3, "gameId": "2009081550"}, {"sequence": 1, "clubcode": "ATL", "playerName": "D.Shockley", "statId": 14, "yards": 0, "gameId": "2009081550"}, {"sequence": 3, "clubcode": "ATL", "playerName": "D.Shockley", "statId": 112, "yards": -1, "gameId": "2009081550"}, {"sequence": 3, "clubcode": "ATL", "playerName": "D.Shockley", "statId": 15, "yards": 15, "gameId": "2009081550"}, {"sequence": 4, "clubcode": "ATL", "playerName": "D.Shockley", "statId": 111, "yards": 15, "gameId": "2009081550"}, {"sequence": 2, "clubcode": "ATL", "playerName": "D.Shockley", "statId": 14, "yards": 0, "gameId": "2009081550"}, {"sequence": 5, "clubcode": "ATL", "playerName": "D.Shockley", "statId": 112, "yards": 5, "gameId": "2009081550"}, {"sequence": 1, "clubcode": "ATL", "playerName": "D.Shockley", "statId": 10, "yards": 4, "gameId": "2009090352"}, {"sequence": 2, "clubcode": "ATL", "playerName": "D.Shockley", "statId": 14, "yards": 0, "gameId": "2009090352"}, {"sequence": 5, "clubcode": "ATL", "playerName": "D.Shockley", "statId": 112, "yards": 6, "gameId": "2009090352"}, {"sequence": 1, "clubcode": "ATL", "playerName": "D.Shockley", "statId": 15, "yards": 6, "gameId": "2009090352"}, {"sequence": 2, "clubcode": "ATL", "playerName": "D.Shockley", "statId": 111, "yards": 6, "gameId": "2009090352"}, {"sequence": 1, "clubcode": "ATL", "playerName": "D.Shockley", "statId": 15, "yards": 9, "gameId": "2009090352"}, {"sequence": 2, "clubcode": "ATL", "playerName": "D.Shockley", "statId": 111, "yards": 9, "gameId": "2009090352"}, {"sequence": 2, "clubcode": "ATL", "playerName": "D.Shockley", "statId": 14, "yards": 0, "gameId": "2009090352"}, {"sequence": 5, "clubcode": "ATL", "playerName": "D.Shockley", "statId": 112, "yards": 18, "gameId": "2009090352"}, {"sequence": 1, "clubcode": "ATL", "playerName": "D.Shockley", "statId": 14, "yards": 0, "gameId": "2009090352"}, {"sequence": 3, "clubcode": "ATL", "playerName": "D.Shockley", "statId": 112, "yards": 6, "gameId": "2009090352"}, {"sequence": 1, "clubcode": "ATL", "playerName": "D.Shockley", "statId": 19, "yards": 0, "gameId": "2009090352"}, {"sequence": 3, "clubcode": "ATL", "playerName": "D.Shockley", "statId": 112, "yards": 29, "gameId": "2009090352"}, {"sequence": 1, "clubcode": "ATL", "playerName": "D.Shockley", "statId": 14, "yards": 0, "gameId": "2009082151"}, {"sequence": 4, "clubcode": "ATL", "playerName": "D.Shockley", "statId": 112, "yards": 10, "gameId": "2009082151"}, {"sequence": 1, "clubcode": "ATL", "playerName": "D.Shockley", "statId": 19, "yards": 0, "gameId": "2009082151"}, {"sequence": 3, "clubcode": "ATL", "playerName": "D.Shockley", "statId": 112, "yards": 8, "gameId": "2009082151"}, {"sequence": 1, "clubcode": "ATL", "playerName": "D.Shockley", "statId": 15, "yards": 3, "gameId": "2009082151"}, {"sequence": 2, "clubcode": "ATL", "playerName": "D.Shockley", "statId": 111, "yards": -2, "gameId": "2009082151"}, {"sequence": 2, "clubcode": "ATL", "playerName": "D.Shockley", "statId": 14, "yards": 0, "gameId": "2009082151"}, {"sequence": 6, "clubcode": "ATL", "playerName": "D.Shockley", "statId": 112, "yards": 21, "gameId": "2009082151"}, {"sequence": 1, "clubcode": "ATL", "playerName": "D.Shockley", "statId": 14, "yards": 0, "gameId": "2009082151"}, {"sequence": 3, "clubcode": "ATL", "playerName": "D.Shockley", "statId": 112, "yards": 6, "gameId": "2009082151"}, {"sequence": 2, "clubcode": "ATL", "playerName": "D.Shockley", "statId": 15, "yards": 4, "gameId": "2009082151"}, {"sequence": 3, "clubcode": "ATL", "playerName": "D.Shockley", "statId": 111, "yards": 4, "gameId": "2009082151"}, {"sequence": 1, "clubcode": "ATL", "playerName": "D.Shockley", "statId": 14, "yards": 0, "gameId": "2009082151"}, {"sequence": 3, "clubcode": "ATL", "playerName": "D.Shockley", "statId": 112, "yards": 39, "gameId": "2009082151"}, {"sequence": 3, "clubcode": "ATL", "playerName": "D.Shockley", "statId": 15, "yards": 16, "gameId": "2009082151"}, {"sequence": 4, "clubcode": "ATL", "playerName": "D.Shockley", "statId": 111, "yards": 14, "gameId": "2009082151"}, {"sequence": 1, "clubcode": "ATL", "playerName": "D.Shockley", "statId": 20, "yards": -7, "gameId": "2009082151"}, {"sequence": 4, "clubcode": "ATL", "playerName": "D.Shockley", "statId": 52, "yards": 0, "gameId": "2009082151"}, {"sequence": 5, "clubcode": "ATL", "playerName": "D.Shockley", "statId": 106, "yards": 0, "gameId": "2009082151"}, {"sequence": 2, "clubcode": "ATL", "playerName": "D.Shockley", "statId": 15, "yards": 23, "gameId": "2009082151"}, {"sequence": 3, "clubcode": "ATL", "playerName": "D.Shockley", "statId": 111, "yards": 0, "gameId": "2009082151"}, {"sequence": 1, "clubcode": "ATL", "playerName": "D.Shockley", "statId": 14, "yards": 0, "gameId": "2009082151"}, {"sequence": 4, "clubcode": "ATL", "playerName": "D.Shockley", "statId": 112, "yards": 23, "gameId": "2009082151"}, {"sequence": 3, "clubcode": "ATL", "playerName": "D.Shockley", "statId": 15, "yards": 17, "gameId": "2009082151"}, {"sequence": 4, "clubcode": "ATL", "playerName": "D.Shockley", "statId": 111, "yards": 11, "gameId": "2009082151"}, {"sequence": 2, "clubcode": "ATL", "playerName": "D.Shockley", "statId": 20, "yards": -1, "gameId": "2009082151"}, {"sequence": 2, "clubcode": "ATL", "playerName": "D.Shockley", "statId": 19, "yards": 0, "gameId": "2009082151"}, {"sequence": 4, "clubcode": "ATL", "playerName": "D.Shockley", "statId": 112, "yards": 20, "gameId": "2009082151"}], "playerName": "D.Shockley"}