{"teams": ["BAL"], "stats": [{"sequence": 2, "clubcode": "BAL", "playerName": "J.Woodrum", "statId": 16, "yards": 33, "gameId": "2017081051"}, {"sequence": 3, "clubcode": "BAL", "playerName": "J.Woodrum", "statId": 111, "yards": 33, "gameId": "2017081051"}, {"sequence": 3, "clubcode": "BAL", "playerName": "J.Woodrum", "statId": 10, "yards": 13, "gameId": "2017081051"}, {"sequence": 2, "clubcode": "BAL", "playerName": "J.Woodrum", "statId": 15, "yards": 14, "gameId": "2017081051"}, {"sequence": 3, "clubcode": "BAL", "playerName": "J.Woodrum", "statId": 111, "yards": 11, "gameId": "2017081051"}, {"sequence": 1, "clubcode": "BAL", "playerName": "J.Woodrum", "statId": 10, "yards": 3, "gameId": "2017081051"}, {"sequence": 2, "clubcode": "BAL", "playerName": "J.Woodrum", "statId": 10, "yards": 1, "gameId": "2017081051"}, {"sequence": 1, "clubcode": "BAL", "playerName": "J.Woodrum", "statId": 15, "yards": 2, "gameId": "2017081051"}, {"sequence": 2, "clubcode": "BAL", "playerName": "J.Woodrum", "statId": 111, "yards": 1, "gameId": "2017081051"}, {"sequence": 3, "clubcode": "BAL", "playerName": "J.Woodrum", "statId": 15, "yards": 36, "gameId": "2017081051"}, {"sequence": 4, "clubcode": "BAL", "playerName": "J.Woodrum", "statId": 111, "yards": 36, "gameId": "2017081051"}, {"sequence": 1, "clubcode": "BAL", "playerName": "J.Woodrum", "statId": 10, "yards": -1, "gameId": "2017081051"}, {"sequence": 1, "clubcode": "BAL", "playerName": "J.Woodrum", "statId": 10, "yards": -1, "gameId": "2017081051"}, {"sequence": 2, "clubcode": "BAL", "playerName": "J.Woodrum", "statId": 15, "yards": 19.0, "gameId": "2017083163"}, {"sequence": 3, "clubcode": "BAL", "playerName": "J.Woodrum", "statId": 111, "yards": 17.0, "gameId": "2017083163"}, {"sequence": 1, "clubcode": "BAL", "playerName": "J.Woodrum", "statId": 10, "yards": 1.0, "gameId": "2017083163"}, {"sequence": 1, "clubcode": "BAL", "playerName": "J.Woodrum", "statId": 15, "yards": 10.0, "gameId": "2017083163"}, {"sequence": 2, "clubcode": "BAL", "playerName": "J.Woodrum", "statId": 111, "yards": -4.0, "gameId": "2017083163"}, {"sequence": 2, "clubcode": "BAL", "playerName": "J.Woodrum", "statId": 15, "yards": 4.0, "gameId": "2017083163"}, {"sequence": 3, "clubcode": "BAL", "playerName": "J.Woodrum", "statId": 111, "yards": 1.0, "gameId": "2017083163"}, {"sequence": 2, "clubcode": "BAL", "playerName": "J.Woodrum", "statId": 15, "yards": 37.0, "gameId": "2017083163"}, {"sequence": 3, "clubcode": "BAL", "playerName": "J.Woodrum", "statId": 111, "yards": 31.0, "gameId": "2017083163"}, {"sequence": 1, "clubcode": "BAL", "playerName": "J.Woodrum", "statId": 14, "yards": 0.0, "gameId": "2017083163"}, {"sequence": 5, "clubcode": "BAL", "playerName": "J.Woodrum", "statId": 112, "yards": 3.0, "gameId": "2017083163"}, {"sequence": 2, "clubcode": "BAL", "playerName": "J.Woodrum", "statId": 15, "yards": 1.0, "gameId": "2017083163"}, {"sequence": 3, "clubcode": "BAL", "playerName": "J.Woodrum", "statId": 111, "yards": 1.0, "gameId": "2017083163"}, {"sequence": 1, "clubcode": "BAL", "playerName": "J.Woodrum", "statId": 14, "yards": 0.0, "gameId": "2017083163"}, {"sequence": 4, "clubcode": "BAL", "playerName": "J.Woodrum", "statId": 112, "yards": 16.0, "gameId": "2017083163"}, {"sequence": 2, "clubcode": "BAL", "playerName": "J.Woodrum", "statId": 14, "yards": 0.0, "gameId": "2017083163"}, {"sequence": 5, "clubcode": "BAL", "playerName": "J.Woodrum", "statId": 112, "yards": 6.0, "gameId": "2017083163"}, {"sequence": 1, "clubcode": "BAL", "playerName": "J.Woodrum", "statId": 10, "yards": 2.0, "gameId": "2017083163"}, {"sequence": 2, "clubcode": "BAL", "playerName": "J.Woodrum", "statId": 14, "yards": 0.0, "gameId": "2017083163"}, {"sequence": 4, "clubcode": "BAL", "playerName": "J.Woodrum", "statId": 112, "yards": 5.0, "gameId": "2017083163"}, {"sequence": 1, "clubcode": "BAL", "playerName": "J.Woodrum", "statId": 10, "yards": -1.0, "gameId": "2017083163"}, {"sequence": 1, "clubcode": "BAL", "playerName": "J.Woodrum", "statId": 14, "yards": 0.0, "gameId": "2018083053"}, {"sequence": 4, "clubcode": "BAL", "playerName": "J.Woodrum", "statId": 112, "yards": 8.0, "gameId": "2018083053"}, {"sequence": 2, "clubcode": "BAL", "playerName": "J.Woodrum", "statId": 14, "yards": 0.0, "gameId": "2018083053"}, {"sequence": 4, "clubcode": "BAL", "playerName": "J.Woodrum", "statId": 112, "yards": 10.0, "gameId": "2018083053"}, {"sequence": 2, "clubcode": "BAL", "playerName": "J.Woodrum", "statId": 15, "yards": 15.0, "gameId": "2018083053"}, {"sequence": 3, "clubcode": "BAL", "playerName": "J.Woodrum", "statId": 111, "yards": 7.0, "gameId": "2018083053"}, {"sequence": 1, "clubcode": "BAL", "playerName": "J.Woodrum", "statId": 14, "yards": 0.0, "gameId": "2018083053"}, {"sequence": 3, "clubcode": "BAL", "playerName": "J.Woodrum", "statId": 112, "yards": 4.0, "gameId": "2018083053"}, {"sequence": 2, "clubcode": "BAL", "playerName": "J.Woodrum", "statId": 16, "yards": 14.0, "gameId": "2018083053"}, {"sequence": 3, "clubcode": "BAL", "playerName": "J.Woodrum", "statId": 111, "yards": 6.0, "gameId": "2018083053"}, {"sequence": 2, "clubcode": "BAL", "playerName": "J.Woodrum", "statId": 15, "yards": 8.0, "gameId": "2018083053"}, {"sequence": 3, "clubcode": "BAL", "playerName": "J.Woodrum", "statId": 111, "yards": 5.0, "gameId": "2018083053"}, {"sequence": 1, "clubcode": "BAL", "playerName": "J.Woodrum", "statId": 19, "yards": 0.0, "gameId": "2018083053"}, {"sequence": 3, "clubcode": "BAL", "playerName": "J.Woodrum", "statId": 112, "yards": 14.0, "gameId": "2018083053"}, {"sequence": 2, "clubcode": "BAL", "playerName": "J.Woodrum", "statId": 14, "yards": 0.0, "gameId": "2018083053"}, {"sequence": 5, "clubcode": "BAL", "playerName": "J.Woodrum", "statId": 112, "yards": -1.0, "gameId": "2018083053"}, {"sequence": 1, "clubcode": "BAL", "playerName": "J.Woodrum", "statId": 10, "yards": -1.0, "gameId": "2018083053"}, {"sequence": 2, "clubcode": "BAL", "playerName": "J.Woodrum", "statId": 15, "yards": 30.0, "gameId": "2018082555"}, {"sequence": 3, "clubcode": "BAL", "playerName": "J.Woodrum", "statId": 111, "yards": 22.0, "gameId": "2018082555"}, {"sequence": 1, "clubcode": "BAL", "playerName": "J.Woodrum", "statId": 15, "yards": 8.0, "gameId": "2018082555"}, {"sequence": 2, "clubcode": "BAL", "playerName": "J.Woodrum", "statId": 111, "yards": 8.0, "gameId": "2018082555"}, {"sequence": 2, "clubcode": "BAL", "playerName": "J.Woodrum", "statId": 15, "yards": 9.0, "gameId": "2018082555"}, {"sequence": 3, "clubcode": "BAL", "playerName": "J.Woodrum", "statId": 111, "yards": -1.0, "gameId": "2018082555"}, {"sequence": 1, "clubcode": "BAL", "playerName": "J.Woodrum", "statId": 14, "yards": 0.0, "gameId": "2018082555"}, {"sequence": 3, "clubcode": "BAL", "playerName": "J.Woodrum", "statId": 112, "yards": 6.0, "gameId": "2018082555"}, {"sequence": 2, "clubcode": "BAL", "playerName": "J.Woodrum", "statId": 14, "yards": 0.0, "gameId": "2018082555"}, {"sequence": 4, "clubcode": "BAL", "playerName": "J.Woodrum", "statId": 112, "yards": 6.0, "gameId": "2018082555"}, {"sequence": 1, "clubcode": "BAL", "playerName": "J.Woodrum", "statId": 10, "yards": -2.0, "gameId": "2018082555"}, {"sequence": 1, "clubcode": "BAL", "playerName": "J.Woodrum", "statId": 10, "yards": -1.0, "gameId": "2018082555"}, {"sequence": 1, "clubcode": "BAL", "playerName": "J.Woodrum", "statId": 15, "yards": 4, "gameId": "2017081752"}, {"sequence": 2, "clubcode": "BAL", "playerName": "J.Woodrum", "statId": 111, "yards": 3, "gameId": "2017081752"}, {"sequence": 2, "clubcode": "BAL", "playerName": "J.Woodrum", "statId": 14, "yards": 0, "gameId": "2017081752"}, {"sequence": 4, "clubcode": "BAL", "playerName": "J.Woodrum", "statId": 112, "yards": 9, "gameId": "2017081752"}, {"sequence": 2, "clubcode": "BAL", "playerName": "J.Woodrum", "statId": 15, "yards": 40, "gameId": "2017081752"}, {"sequence": 3, "clubcode": "BAL", "playerName": "J.Woodrum", "statId": 111, "yards": 0, "gameId": "2017081752"}, {"sequence": 2, "clubcode": "BAL", "playerName": "J.Woodrum", "statId": 11, "yards": 14, "gameId": "2017081752"}, {"sequence": 1, "clubcode": "BAL", "playerName": "J.Woodrum", "statId": 77, "yards": 0, "gameId": "2017081752"}, {"sequence": 3, "clubcode": "BAL", "playerName": "J.Woodrum", "statId": 15, "yards": 4, "gameId": "2017081752"}, {"sequence": 4, "clubcode": "BAL", "playerName": "J.Woodrum", "statId": 111, "yards": 4, "gameId": "2017081752"}, {"sequence": 2, "clubcode": "BAL", "playerName": "J.Woodrum", "statId": 15, "yards": 17, "gameId": "2017081752"}, {"sequence": 3, "clubcode": "BAL", "playerName": "J.Woodrum", "statId": 111, "yards": 0, "gameId": "2017081752"}, {"sequence": 1, "clubcode": "BAL", "playerName": "J.Woodrum", "statId": 10, "yards": 0, "gameId": "2017081752"}, {"sequence": 2, "clubcode": "BAL", "playerName": "J.Woodrum", "statId": 57, "yards": -3, "gameId": "2017081752"}, {"sequence": 3, "clubcode": "BAL", "playerName": "J.Woodrum", "statId": 53, "yards": 0, "gameId": "2017081752"}, {"sequence": 3, "clubcode": "BAL", "playerName": "J.Woodrum", "statId": 11, "yards": 1, "gameId": "2017081752"}, {"sequence": 3, "clubcode": "BAL", "playerName": "J.Woodrum", "statId": 15, "yards": 20, "gameId": "2017081752"}, {"sequence": 4, "clubcode": "BAL", "playerName": "J.Woodrum", "statId": 111, "yards": 17, "gameId": "2017081752"}, {"sequence": 1, "clubcode": "BAL", "playerName": "J.Woodrum", "statId": 15, "yards": 7, "gameId": "2017081752"}, {"sequence": 2, "clubcode": "BAL", "playerName": "J.Woodrum", "statId": 111, "yards": -3, "gameId": "2017081752"}, {"sequence": 3, "clubcode": "BAL", "playerName": "J.Woodrum", "statId": 15, "yards": 10, "gameId": "2017081752"}, {"sequence": 4, "clubcode": "BAL", "playerName": "J.Woodrum", "statId": 111, "yards": 9, "gameId": "2017081752"}, {"sequence": 1, "clubcode": "BAL", "playerName": "J.Woodrum", "statId": 14, "yards": 0, "gameId": "2017081752"}, {"sequence": 3, "clubcode": "BAL", "playerName": "J.Woodrum", "statId": 112, "yards": 27, "gameId": "2017081752"}, {"sequence": 2, "clubcode": "BAL", "playerName": "J.Woodrum", "statId": 15, "yards": 8, "gameId": "2017081752"}, {"sequence": 3, "clubcode": "BAL", "playerName": "J.Woodrum", "statId": 111, "yards": 6, "gameId": "2017081752"}, {"sequence": 1, "clubcode": "BAL", "playerName": "J.Woodrum", "statId": 10, "yards": 4, "gameId": "2017082652"}, {"sequence": 2, "clubcode": "BAL", "playerName": "J.Woodrum", "statId": 14, "yards": 0, "gameId": "2017082652"}, {"sequence": 4, "clubcode": "BAL", "playerName": "J.Woodrum", "statId": 112, "yards": 23, "gameId": "2017082652"}, {"sequence": 2, "clubcode": "BAL", "playerName": "J.Woodrum", "statId": 14, "yards": 0, "gameId": "2017082652"}, {"sequence": 3, "clubcode": "BAL", "playerName": "J.Woodrum", "statId": 112, "yards": 0, "gameId": "2017082652"}, {"sequence": 4, "clubcode": "BAL", "playerName": "J.Woodrum", "statId": 93, "yards": 25, "gameId": "2017082652"}, {"sequence": 1, "clubcode": "BAL", "playerName": "J.Woodrum", "statId": 15, "yards": 8, "gameId": "2017082652"}, {"sequence": 2, "clubcode": "BAL", "playerName": "J.Woodrum", "statId": 111, "yards": 8, "gameId": "2017082652"}, {"sequence": 1, "clubcode": "BAL", "playerName": "J.Woodrum", "statId": 15, "yards": 7, "gameId": "2017082652"}, {"sequence": 2, "clubcode": "BAL", "playerName": "J.Woodrum", "statId": 111, "yards": 7, "gameId": "2017082652"}, {"sequence": 2, "clubcode": "BAL", "playerName": "J.Woodrum", "statId": 15, "yards": 0, "gameId": "2017082652"}, {"sequence": 3, "clubcode": "BAL", "playerName": "J.Woodrum", "statId": 111, "yards": -4, "gameId": "2017082652"}, {"sequence": 1, "clubcode": "BAL", "playerName": "J.Woodrum", "statId": 10, "yards": -1, "gameId": "2017082652"}, {"sequence": 1, "clubcode": "BAL", "playerName": "J.Woodrum", "statId": 15, "yards": 8, "gameId": "2017082652"}, {"sequence": 2, "clubcode": "BAL", "playerName": "J.Woodrum", "statId": 111, "yards": 8, "gameId": "2017082652"}, {"sequence": 2, "clubcode": "BAL", "playerName": "J.Woodrum", "statId": 15, "yards": 2, "gameId": "2017082652"}, {"sequence": 3, "clubcode": "BAL", "playerName": "J.Woodrum", "statId": 111, "yards": 1, "gameId": "2017082652"}, {"sequence": 1, "clubcode": "BAL", "playerName": "J.Woodrum", "statId": 14, "yards": 0, "gameId": "2017082652"}, {"sequence": 4, "clubcode": "BAL", "playerName": "J.Woodrum", "statId": 112, "yards": 9, "gameId": "2017082652"}, {"sequence": 3, "clubcode": "BAL", "playerName": "J.Woodrum", "statId": 15, "yards": 9, "gameId": "2017082652"}, {"sequence": 4, "clubcode": "BAL", "playerName": "J.Woodrum", "statId": 111, "yards": 5, "gameId": "2017082652"}, {"sequence": 2, "clubcode": "BAL", "playerName": "J.Woodrum", "statId": 14, "yards": 0, "gameId": "2017082652"}, {"sequence": 5, "clubcode": "BAL", "playerName": "J.Woodrum", "statId": 112, "yards": 6, "gameId": "2017082652"}, {"sequence": 1, "clubcode": "BAL", "playerName": "J.Woodrum", "statId": 14, "yards": 0, "gameId": "2017082652"}, {"sequence": 4, "clubcode": "BAL", "playerName": "J.Woodrum", "statId": 112, "yards": 23, "gameId": "2017082652"}, {"sequence": 1, "clubcode": "BAL", "playerName": "J.Woodrum", "statId": 10, "yards": 4, "gameId": "2017082652"}, {"sequence": 2, "clubcode": "BAL", "playerName": "J.Woodrum", "statId": 10, "yards": 3, "gameId": "2017082652"}, {"sequence": 1, "clubcode": "BAL", "playerName": "J.Woodrum", "statId": 53, "yards": 0, "gameId": "2017082652"}, {"sequence": 2, "clubcode": "BAL", "playerName": "J.Woodrum", "statId": 55, "yards": 0, "gameId": "2017082652"}, {"sequence": 3, "clubcode": "BAL", "playerName": "J.Woodrum", "statId": 10, "yards": 0, "gameId": "2017082652"}, {"sequence": 4, "clubcode": "BAL", "playerName": "J.Woodrum", "statId": 57, "yards": -6, "gameId": "2017082652"}, {"sequence": 1, "clubcode": "BAL", "playerName": "J.Woodrum", "statId": 15, "yards": 6, "gameId": "2017082652"}, {"sequence": 2, "clubcode": "BAL", "playerName": "J.Woodrum", "statId": 111, "yards": 6, "gameId": "2017082652"}, {"sequence": 3, "clubcode": "BAL", "playerName": "J.Woodrum", "statId": 16, "yards": 15, "gameId": "2017082652"}, {"sequence": 4, "clubcode": "BAL", "playerName": "J.Woodrum", "statId": 111, "yards": 10, "gameId": "2017082652"}], "playerName": "J.Woodrum"}