{"teams": ["NE", "NO"], "stats": [{"sequence": 1, "clubcode": "NE", "playerName": "C.Taylor", "statId": 10, "yards": 1, "gameId": "2010081252"}, {"sequence": 1, "clubcode": "NE", "playerName": "C.Taylor", "statId": 10, "yards": 8, "gameId": "2010081252"}, {"sequence": 1, "clubcode": "NE", "playerName": "C.Taylor", "statId": 10, "yards": 4, "gameId": "2010081252"}, {"sequence": 4, "clubcode": "NE", "playerName": "C.Taylor", "statId": 21, "yards": -7, "gameId": "2010081252"}, {"sequence": 5, "clubcode": "NE", "playerName": "C.Taylor", "statId": 115, "yards": 0, "gameId": "2010081252"}, {"sequence": 6, "clubcode": "NE", "playerName": "C.Taylor", "statId": 113, "yards": -1, "gameId": "2010081252"}, {"sequence": 1, "clubcode": "NE", "playerName": "C.Taylor", "statId": 10, "yards": 7, "gameId": "2010081252"}, {"sequence": 2, "clubcode": "NE", "playerName": "C.Taylor", "statId": 10, "yards": 4, "gameId": "2010081252"}, {"sequence": 1, "clubcode": "NE", "playerName": "C.Taylor", "statId": 10, "yards": 6, "gameId": "2010081252"}, {"sequence": 1, "clubcode": "NE", "playerName": "C.Taylor", "statId": 10, "yards": 3, "gameId": "2010081252"}, {"sequence": 1, "clubcode": "NE", "playerName": "C.Taylor", "statId": 10, "yards": 6, "gameId": "2010081252"}, {"sequence": 3, "clubcode": "NE", "playerName": "C.Taylor", "statId": 115, "yards": 0, "gameId": "2010081252"}, {"sequence": 2, "clubcode": "NO", "playerName": "C.Taylor", "statId": 10, "yards": 5, "gameId": "2011082051"}, {"sequence": 1, "clubcode": "NO", "playerName": "C.Taylor", "statId": 10, "yards": 3, "gameId": "2011082051"}, {"sequence": 1, "clubcode": "NO", "playerName": "C.Taylor", "statId": 10, "yards": 3, "gameId": "2011082051"}, {"sequence": 3, "clubcode": "NO", "playerName": "C.Taylor", "statId": 10, "yards": 2, "gameId": "2011082051"}, {"sequence": 1, "clubcode": "NO", "playerName": "C.Taylor", "statId": 21, "yards": 9, "gameId": "2011082051"}, {"sequence": 2, "clubcode": "NO", "playerName": "C.Taylor", "statId": 115, "yards": 0, "gameId": "2011082051"}, {"sequence": 8, "clubcode": "NO", "playerName": "C.Taylor", "statId": 113, "yards": 11, "gameId": "2011082051"}, {"sequence": 1, "clubcode": "NE", "playerName": "C.Taylor", "statId": 10, "yards": 2, "gameId": "2009090354"}, {"sequence": 2, "clubcode": "NE", "playerName": "C.Taylor", "statId": 45, "yards": 22, "gameId": "2009090354"}, {"sequence": 4, "clubcode": "NE", "playerName": "C.Taylor", "statId": 82, "yards": 0, "gameId": "2010082652"}, {"sequence": 1, "clubcode": "NO", "playerName": "C.Taylor", "statId": 10, "yards": 5, "gameId": "2011081254"}, {"sequence": 2, "clubcode": "NO", "playerName": "C.Taylor", "statId": 11, "yards": 4, "gameId": "2011081254"}, {"sequence": 1, "clubcode": "NO", "playerName": "C.Taylor", "statId": 10, "yards": 2, "gameId": "2011081254"}, {"sequence": 1, "clubcode": "NO", "playerName": "C.Taylor", "statId": 10, "yards": 3, "gameId": "2011081254"}, {"sequence": 1, "clubcode": "NO", "playerName": "C.Taylor", "statId": 10, "yards": 6, "gameId": "2011081254"}, {"sequence": 3, "clubcode": "NO", "playerName": "C.Taylor", "statId": 10, "yards": 5, "gameId": "2011081254"}, {"sequence": 1, "clubcode": "NO", "playerName": "C.Taylor", "statId": 10, "yards": 7, "gameId": "2011081254"}, {"sequence": 2, "clubcode": "NO", "playerName": "C.Taylor", "statId": 10, "yards": 4, "gameId": "2011081254"}, {"sequence": 1, "clubcode": "NO", "playerName": "C.Taylor", "statId": 10, "yards": 3, "gameId": "2011081254"}, {"sequence": 3, "clubcode": "NE", "playerName": "C.Taylor", "statId": 79, "yards": 0, "gameId": "2010090253"}, {"sequence": 2, "clubcode": "NE", "playerName": "C.Taylor", "statId": 10, "yards": 10, "gameId": "2009082850"}, {"sequence": 1, "clubcode": "NE", "playerName": "C.Taylor", "statId": 10, "yards": 9, "gameId": "2009082850"}, {"sequence": 2, "clubcode": "NE", "playerName": "C.Taylor", "statId": 10, "yards": 5, "gameId": "2009082850"}, {"sequence": 1, "clubcode": "NE", "playerName": "C.Taylor", "statId": 10, "yards": 1, "gameId": "2009082850"}, {"sequence": 3, "clubcode": "NE", "playerName": "C.Taylor", "statId": 52, "yards": 0, "gameId": "2009082850"}, {"sequence": 4, "clubcode": "NE", "playerName": "C.Taylor", "statId": 106, "yards": 0, "gameId": "2009082850"}, {"sequence": 4, "clubcode": "NE", "playerName": "C.Taylor", "statId": 21, "yards": 10, "gameId": "2009082051"}, {"sequence": 5, "clubcode": "NE", "playerName": "C.Taylor", "statId": 115, "yards": 0, "gameId": "2009082051"}, {"sequence": 6, "clubcode": "NE", "playerName": "C.Taylor", "statId": 113, "yards": 6, "gameId": "2009082051"}], "totals": {"10": {"statId": 10, "count": 25, "totYds": 114}, "21": {"statId": 21, "count": 3, "totYds": 12}, "115": {"statId": 115, "count": 4, "totYds": 0}, "113": {"statId": 113, "count": 3, "totYds": 16}, "45": {"statId": 45, "count": 1, "totYds": 22}, "82": {"statId": 82, "count": 1, "totYds": 0}, "11": {"statId": 11, "count": 1, "totYds": 4}, "79": {"statId": 79, "count": 1, "totYds": 0}, "52": {"statId": 52, "count": 1, "totYds": 0}, "106": {"statId": 106, "count": 1, "totYds": 0}}, "playerName": "C.Taylor"}